rabbitgetapi/__init__.py
rabbitgetapi/__main__.py
rabbitgetapi/build_parser.py
rabbitgetapi/cli.py
rabbitgetapi/exceptions.py
rabbitgetapi/settings.py
rabbitgetapi/commands/__init__.py
rabbitgetapi/commands/get_queue.py
rabbitgetapi-0.0.2.dist-info/LICENSE
rabbitgetapi-0.0.2.dist-info/METADATA
rabbitgetapi-0.0.2.dist-info/WHEEL
rabbitgetapi-0.0.2.dist-info/entry_points.txt
rabbitgetapi-0.0.2.dist-info/top_level.txt
rabbitgetapi-0.0.2.dist-info/RECORD
