Metadata-Version: 2.1
Name: rabbitgetapi
Version: 0.0.2
Summary: Get RabbitMQ messages from a specific queue to a file.
Home-page: UNKNOWN
Author: Sidon Duarte and individual contributors
Author-email: sidoncd@gmail.com
License: UNKNOWN
Project-URL: Source, https://github.com/Sidon/rabbitgetapi
Project-URL: Bug Tracker, https://github.com/Sidon/rabbitgetapi/issues
Platform: UNKNOWN
Classifier: Intended Audience :: Developers
Classifier: Natural Language :: English
Classifier: Programming Language :: Python :: 3
Classifier: License :: OSI Approved :: MIT License
Classifier: Operating System :: OS Independent
Requires-Python: >=3.6
License-File: LICENSE
Requires-Dist: requests (>=2.20)
Requires-Dist: importlib-metadata (>=3.6)
Requires-Dist: colorama (>=0.4.3)
